SensitiveImageDetect/__init__.py
sensitive_image-0.1.0.dist-info/METADATA
sensitive_image-0.1.0.dist-info/WHEEL
sensitive_image-0.1.0.dist-info/top_level.txt
sensitive_image-0.1.0.dist-info/RECORD
