Metadata-Version: 2.1
Name: sensitive_image
Version: 0.1.0
Summary: A package used to detect sensitive image
Home-page: https://github.com/W1412X/sensitive-image-detect-model
Author: W1412X
Author-email: w108418@126.com
Classifier: Programming Language :: Python :: 3
Classifier: License :: OSI Approved :: MIT License
Classifier: Operating System :: OS Independent
Requires-Dist: torch
Requires-Dist: torchvision
Requires-Dist: pillow
